xinference/__init__.py
xinference/_version.py
xinference/client.py
xinference/conftest.py
xinference/constants.py
xinference/isolation.py
xinference/types.py
xinference/core/__init__.py
xinference/core/api.py
xinference/core/chat_interface.py
xinference/core/model.py
xinference/core/resource.py
xinference/core/restful_api.py
xinference/core/supervisor.py
xinference/core/utils.py
xinference/core/worker.py
xinference/deploy/__init__.py
xinference/deploy/cmdline.py
xinference/deploy/local.py
xinference/deploy/supervisor.py
xinference/deploy/utils.py
xinference/deploy/worker.py
xinference/deploy/test/__init__.py
xinference/deploy/test/test_cmdline.py
xinference/locale/__init__.py
xinference/locale/utils.py
xinference/locale/zh_CN.json
xinference/model/__init__.py
xinference/model/core.py
xinference/model/embedding/__init__.py
xinference/model/embedding/core.py
xinference/model/llm/__init__.py
xinference/model/llm/core.py
xinference/model/llm/llm_family.json
xinference/model/llm/llm_family.py
xinference/model/llm/utils.py
xinference/model/llm/ggml/__init__.py
xinference/model/llm/ggml/chatglm.py
xinference/model/llm/ggml/ctransformers.py
xinference/model/llm/ggml/ctransformers_util.py
xinference/model/llm/ggml/llamacpp.py
xinference/model/llm/pytorch/__init__.py
xinference/model/llm/pytorch/baichuan.py
xinference/model/llm/pytorch/chatglm.py
xinference/model/llm/pytorch/compression.py
xinference/model/llm/pytorch/core.py
xinference/model/llm/pytorch/falcon.py
xinference/model/llm/pytorch/llama_2.py
xinference/model/llm/pytorch/utils.py
xinference/model/llm/pytorch/vicuna.py
xinference/web/ui/build/asset-manifest.json
xinference/web/ui/build/favicon.svg
xinference/web/ui/build/index.html
xinference/web/ui/build/static/js/main.c4459721.js
xinference/web/ui/build/static/js/main.c4459721.js.LICENSE.txt
xinference/web/ui/build/static/js/main.c4459721.js.map
xinference/web/ui/build/static/media/icon.4603d52c63041e5dfbfd.webp
xinference-0.4.0.dist-info/LICENSE
xinference-0.4.0.dist-info/METADATA
xinference-0.4.0.dist-info/WHEEL
xinference-0.4.0.dist-info/entry_points.txt
xinference-0.4.0.dist-info/top_level.txt
xinference-0.4.0.dist-info/RECORD
