Metadata-Version: 2.1
Name: xinference
Version: 0.4.0
Summary: Model Serving Made Easy
Home-page: https://github.com/xorbitsai/inference
Author: Qin Xuye
Author-email: qinxuye@xprobe.io
Maintainer: Qin Xuye
Maintainer-email: qinxuye@xprobe.io
License: Apache License 2.0
Classifier: Operating System :: OS Independent
Classifier: Programming Language :: Python
Classifier: Programming Language :: Python :: 3
Classifier: Programming Language :: Python :: 3.8
Classifier: Programming Language :: Python :: 3.9
Classifier: Programming Language :: Python :: 3.10
Classifier: Programming Language :: Python :: 3.11
Classifier: Programming Language :: Python :: Implementation :: CPython
Classifier: Topic :: Software Development :: Libraries
License-File: LICENSE
Requires-Dist: xoscar
Requires-Dist: xorbits
Requires-Dist: gradio >=3.39.0
Requires-Dist: click
Requires-Dist: tqdm >=4.27
Requires-Dist: tabulate
Requires-Dist: requests
Requires-Dist: pydantic <2
Requires-Dist: fastapi
Requires-Dist: uvicorn
Requires-Dist: sse-starlette
Requires-Dist: huggingface-hub <1.0,>=0.14.1
Requires-Dist: typing-extensions
Requires-Dist: fsspec
Provides-Extra: all
Requires-Dist: ctransformers ; extra == 'all'
Requires-Dist: llama-cpp-python ==0.1.77 ; extra == 'all'
Requires-Dist: transformers >=4.31.0 ; extra == 'all'
Requires-Dist: torch ; extra == 'all'
Requires-Dist: accelerate >=0.20.3 ; extra == 'all'
Requires-Dist: sentencepiece ; extra == 'all'
Requires-Dist: transformers-stream-generator ; extra == 'all'
Requires-Dist: bitsandbytes ; extra == 'all'
Requires-Dist: protobuf ; extra == 'all'
Requires-Dist: einops ; extra == 'all'
Requires-Dist: tiktoken ; extra == 'all'
Requires-Dist: sentence-transformers ; extra == 'all'
Provides-Extra: benchmark
Requires-Dist: psutil ; extra == 'benchmark'
Requires-Dist: pynvml ; extra == 'benchmark'
Provides-Extra: dev
Requires-Dist: cython >=0.29 ; extra == 'dev'
Requires-Dist: pytest >=3.5.0 ; extra == 'dev'
Requires-Dist: pytest-cov >=2.5.0 ; extra == 'dev'
Requires-Dist: pytest-timeout >=1.2.0 ; extra == 'dev'
Requires-Dist: pytest-forked >=1.0 ; extra == 'dev'
Requires-Dist: pytest-asyncio >=0.14.0 ; extra == 'dev'
Requires-Dist: pytest-mock >=3.11.1 ; extra == 'dev'
Requires-Dist: ipython >=6.5.0 ; extra == 'dev'
Requires-Dist: sphinx <5.0.0,>=3.0.0 ; extra == 'dev'
Requires-Dist: pydata-sphinx-theme >=0.3.0 ; extra == 'dev'
Requires-Dist: sphinx-intl >=0.9.9 ; extra == 'dev'
Requires-Dist: jieba >=0.42.0 ; extra == 'dev'
Requires-Dist: flake8 >=3.8.0 ; extra == 'dev'
Requires-Dist: black ; extra == 'dev'
Provides-Extra: doc
Requires-Dist: ipython >=6.5.0 ; extra == 'doc'
Requires-Dist: sphinx <5.0.0,>=3.0.0 ; extra == 'doc'
Requires-Dist: pydata-sphinx-theme >=0.3.0 ; extra == 'doc'
Requires-Dist: sphinx-intl >=0.9.9 ; extra == 'doc'
Provides-Extra: embedding
Requires-Dist: sentence-transformers ; extra == 'embedding'
Provides-Extra: ggml
Requires-Dist: llama-cpp-python ==0.1.77 ; extra == 'ggml'
Requires-Dist: ctransformers ; extra == 'ggml'
Provides-Extra: pytorch
Requires-Dist: transformers >=4.31.0 ; extra == 'pytorch'
Requires-Dist: torch ; extra == 'pytorch'
Requires-Dist: accelerate >=0.20.3 ; extra == 'pytorch'
Requires-Dist: sentencepiece ; extra == 'pytorch'
Requires-Dist: transformers-stream-generator ; extra == 'pytorch'
Requires-Dist: bitsandbytes ; extra == 'pytorch'
Requires-Dist: protobuf ; extra == 'pytorch'
Requires-Dist: einops ; extra == 'pytorch'
Requires-Dist: tiktoken ; extra == 'pytorch'
